LICENSE
MANIFEST.in
README.md
requirements.txt
setup.cfg
setup.py
notebook_toggle_code/__init__.py
notebook_toggle_code/__meta__.py
notebook_toggle_code/demo_calculator.py
notebook_toggle_code/toggle_code.py
notebook_toggle_code.egg-info/PKG-INFO
notebook_toggle_code.egg-info/SOURCES.txt
notebook_toggle_code.egg-info/dependency_links.txt
notebook_toggle_code.egg-info/requires.txt
notebook_toggle_code.egg-info/top_level.txt
notebook_toggle_code/templates/bootstrapButtons.css
notebook_toggle_code/templates/demoCalculator.html
notebook_toggle_code/templates/main.html
notebook_toggle_code/templates/notice_long.md
notebook_toggle_code/templates/notice_safe.txt
notebook_toggle_code/templates/notice_short.md
notebook_toggle_code/templates/toggleCode.js