Metadata-Version: 1.1
Name: notebook-toggle-code
Version: 0.1.0
Summary: Alow user to toggle code cells - if notebook is trusted
Home-page: https://github.com/oscar6echo/notebook_toggle_code
Author: oscar6echo
Author-email: olivier.borderies@gmail.com
License: MIT
Download-URL: https://github.com/oscar6echo/notebook_toggle_code/tarball/0.1.0
Keywords: python,display,javascript
Platform: UNKNOWN
Classifier: Development Status :: 4 - Beta
Classifier: License :: OSI Approved :: MIT License
Classifier: Programming Language :: Python :: 2.7
Classifier: Programming Language :: Python :: 3.5
Classifier: Programming Language :: Python :: 3.6
